{
    "Ar36": {
        "error": 0.00041742693636450247,
        "error_type": "SEM",
        "filter_outliers_dict": {
            "filter_outliers": true,
            "iterations": 1,
            "std_devs": 2
        },
        "fit": "Linear",
        "fn": 0,
        "include_baseline_error": false,
        "n": 0,
        "reviewed": false,
        "value": 0.02326866374666846
    },
    "Ar37": {
        "error": 0.010927309175967775,
        "error_type": "SEM",
        "filter_outliers_dict": {
            "filter_outliers": true,
            "iterations": 1,
            "std_devs": 2
        },
        "fit": "linear",
        "fn": 0,
        "include_baseline_error": false,
        "n": 0,
        "reviewed": false,
        "value": 1.26424067030307
    },
    "Ar38": {
        "error": 0.005245031354734051,
        "error_type": "SEM",
        "filter_outliers_dict": {
            "filter_outliers": true,
            "iterations": 1,
            "std_devs": 2
        },
        "fit": "linear",
        "fn": 0,
        "include_baseline_error": false,
        "n": 0,
        "reviewed": false,
        "value": 3.612011577533076
    },
    "Ar39": {
        "error": 0.04020976818847513,
        "error_type": "SEM",
        "filter_outliers_dict": {
            "filter_outliers": true,
            "iterations": 1,
            "std_devs": 2
        },
        "fit": "Linear",
        "fn": 0,
        "include_baseline_error": false,
        "n": 0,
        "reviewed": false,
        "value": 308.20936860486194
    },
    "Ar40": {
        "error": 0.07018755132606164,
        "error_type": "SEM",
        "filter_outliers_dict": {
            "filter_outliers": true,
            "iterations": 1,
            "std_devs": 2
        },
        "fit": "Linear",
        "fn": 0,
        "include_baseline_error": false,
        "n": 0,
        "reviewed": false,
        "value": 1203.0944825867384
    },
    "Ar41": {
        "error": 0.005575859663171663,
        "error_type": "SEM",
        "filter_outliers_dict": {
            "filter_outliers": true,
            "iterations": 1,
            "std_devs": 2
        },
        "fit": "Average",
        "fn": 0,
        "include_baseline_error": false,
        "n": 0,
        "reviewed": false,
        "value": 0.01585532758710948
    }
}