{
    "AX": {
        "error": 0.006481566932052374,
        "error_type": "SEM",
        "filter_outliers_dict": {
            "filter_outliers": true,
            "iterations": 1,
            "std_devs": 2
        },
        "fit": "average",
        "fn": 0,
        "include_baseline_error": false,
        "n": 0,
        "reviewed": false,
        "value": -0.09498921226881644
    },
    "CDD": {
        "error": 1.71461815625662e-05,
        "error_type": "SEM",
        "filter_outliers_dict": {
            "filter_outliers": true,
            "iterations": 1,
            "std_devs": 10
        },
        "fit": "average",
        "fn": 0,
        "include_baseline_error": false,
        "n": 0,
        "reviewed": false,
        "value": 0.0001242190040096098
    },
    "H1": {
        "error": 0.005968950688838959,
        "error_type": "SEM",
        "filter_outliers_dict": {
            "filter_outliers": true,
            "iterations": 1,
            "std_devs": 2
        },
        "fit": "average",
        "fn": 0,
        "include_baseline_error": false,
        "n": 0,
        "reviewed": false,
        "value": -0.058154901306821494
    },
    "H2": {
        "error": 0.00407066335901618,
        "error_type": "SEM",
        "filter_outliers_dict": {
            "filter_outliers": true,
            "iterations": 1,
            "std_devs": 2
        },
        "fit": "average",
        "fn": 0,
        "include_baseline_error": false,
        "n": 0,
        "reviewed": false,
        "value": -0.06404847083332058
    },
    "L1": {
        "error": 0.002532434184104204,
        "error_type": "SEM",
        "filter_outliers_dict": {
            "filter_outliers": true,
            "iterations": 1,
            "std_devs": 2
        },
        "fit": "average",
        "fn": 0,
        "include_baseline_error": false,
        "n": 0,
        "reviewed": false,
        "value": 0.03600648040732879
    },
    "L2": {
        "error": 0.005407169461250305,
        "error_type": "SEM",
        "filter_outliers_dict": {
            "filter_outliers": true,
            "iterations": 1,
            "std_devs": 2
        },
        "fit": "average",
        "fn": 0,
        "include_baseline_error": false,
        "n": 0,
        "reviewed": false,
        "value": 0.05307297024978482
    }
}